CHANGELOG.txt
LICENSE.txt
MANIFEST.in
README.txt
setup.cfg
setup.py
loadsure_api_classes/__init__.py
loadsure_api_classes/holistics_api.py
loadsure_api_classes.egg-info/PKG-INFO
loadsure_api_classes.egg-info/SOURCES.txt
loadsure_api_classes.egg-info/dependency_links.txt
loadsure_api_classes.egg-info/top_level.txt