Metadata-Version: 2.1
Name: loadsure-api-classes
Version: 0.1
Summary: Api classes to make a data integration
Home-page: UNKNOWN
Author: Juan Valencia
Author-email: juan.valencia@loadsure.net
License: MIT
Platform: UNKNOWN
Classifier: Development Status :: 1 - Planning
Classifier: Intended Audience :: Developers
Classifier: Operating System :: MacOS
Classifier: Operating System :: Microsoft
Classifier: License :: OSI Approved :: MIT License
Classifier: Programming Language :: Python :: 3.9
License-File: LICENSE.txt
